ctrlmaniac/__init__.py
ctrlmaniac/__main__.py
ctrlmaniac/ctrlmaniac.py
ctrlmaniac-0.3.2.dist-info/WHEEL
ctrlmaniac-0.3.2.dist-info/METADATA
ctrlmaniac-0.3.2.dist-info/RECORD
